{
  "age": 26,
  "name": "Mohamed Aymen BEN MAHFOUDH",
  "adresse": "tunis",
  "mail": "ben.mahfoudh.med.aymen@gmail.com",
  "studies": [],
  "num": "21239484",
  "skills": [
    "c#",
    "rest",
    "c++",
    "c",
    "kvm",
    "oracle",
    "ubuntu",
    "android",
    "sql",
    "eclipse",
    "java",
    "shell",
    "uml",
    "xml",
    "linux",
    ".net",
    "json",
    "php",
    "html",
    "mysql",
    "mvc"
  ],
  "keywords": {
    "se´curite´": 3,
    "suse": 4,
    "protocole": 4,
    "sql": 4,
    "taˆches": 3,
    "ensi": 3,
    "maghreb": 3,
    "linux": 6,
    "mysql": 3,
    "de´veloppe´": 3,
    "a`": 9,
    "nova": 3,
    "utilisation": 3,
    "de´veloppement": 3,
    "ve´rification": 3,
    "c": 7,
    "lpi": 8,
    "ubuntu": 3,
    "identifiant": 3,
    "mene´es": 3,
    "syste`me": 4,
    "re´seaux": 12,
    "·": 10,
    "nabeul": 3,
    "syste`mes": 3
  }
}
